getosm/VERSION
getosm/__init__.py
getosm/getosm.py
getosm/osmtk.py
getosm/osmwx.py
getosm-0.1.2.dist-info/LICENSE
getosm-0.1.2.dist-info/METADATA
getosm-0.1.2.dist-info/WHEEL
getosm-0.1.2.dist-info/entry_points.txt
getosm-0.1.2.dist-info/top_level.txt
getosm-0.1.2.dist-info/RECORD
