Metadata-Version: 2.1
Name: getosm
Version: 0.1.2
Summary: GetOSM is an OpenStreetMap downloader written in Python that is agnostic of GUI frameworks.
Home-page: https://github.com/HuidaeCho/getosm
Author: Huidae Cho
Author-email: grass4u@gmail.com
License: GPLv3+
Platform: UNKNOWN
Classifier: Programming Language :: Python :: 3
Classifier: License :: OSI Approved :: GNU General Public License v3 or later (GPLv3+)
Classifier: Operating System :: OS Independent
Requires-Python: >=3
License-File: LICENSE
